gravityzone/__init__.py
gravityzone/client.py
gravityzone/exceptions.py
gravityzone/models.py
gravityzone/py.typed
gravityzone-0.0.1.dev1.dist-info/LICENSE
gravityzone-0.0.1.dev1.dist-info/METADATA
gravityzone-0.0.1.dev1.dist-info/WHEEL
gravityzone-0.0.1.dev1.dist-info/top_level.txt
gravityzone-0.0.1.dev1.dist-info/RECORD
